{
  "boxs": [
    {
      "Object_type": "Vehicles",
      "x": 0,
      "y": 441.9095434879999,
      "w": 346.00046521599984,
      "h": 294.9991531199999,
      "id": "ui-rect-0",
      "Category": "Truck",
      "Occlusion": "No occlusion (0%)",
      "Direction": "Left",
      "Truncation": "Others (more than 50%)"
    },
    {
      "Object_type": "Vehicles",
      "x": 388.3137684159999,
      "y": 523.4221489279998,
      "w": 156.12223983999996,
      "h": 128.57059196799995,
      "id": "ui-rect-1",
      "Category": "Truck",
      "Occlusion": "No occlusion (0%)",
      "Direction": "Front",
      "Truncation": "No truncation (0%)"
    },
    {
      "Object_type": "Vehicles",
      "x": 997.1203177599997,
      "y": 572.8470988799997,
      "w": 265.3058900799999,
      "h": 89.64988255999997,
      "id": "ui-rect-2",
      "Category": "Sedan",
      "Occlusion": "No occlusion (0%)",
      "Direction": "Right",
      "Truncation": "No truncation (0%)"
    },
    {
      "Object_type": "MISC",
      "x": 1353.8912463999995,
      "y": 610.0268719999998,
      "w": 160.35007430399995,
      "h": 83.09058105599998,
      "id": "ui-rect-3",
      "Category": "Vehicles"
    }
  ],
  "Workload": {
    "Pedestrians": 0,
    "Vehicles": 3,
    "Traffic lights": 0,
    "Indication signs": 0,
    "Prohibitory signs": 0,
    "MISC": 1,
    "Dontcare": 0
  }
}