{
  "boxs": [
    {
      "Object_type": "Vehicles",
      "x": 2.0222150121065376,
      "y": 977.5511476997578,
      "w": 141.39987602905566,
      "h": 405.99631961259075,
      "id": "ui-rect-0",
      "Category": "Sedan",
      "Occlusion": "No occlusion (0%)",
      "Direction": "Left",
      "Truncation": "Others (more than 50%)"
    },
    {
      "Object_type": "Vehicles",
      "x": 0,
      "y": 1004.459622276029,
      "w": 162.4575225181598,
      "h": 189.2869191283293,
      "id": "ui-rect-1",
      "Category": "Sedan",
      "Occlusion": "Partial occlusion (0%~35%)",
      "Direction": "Left",
      "Truncation": "Partial truncation (15%~35%)"
    },
    {
      "Object_type": "Vehicles",
      "x": 133.88778305084745,
      "y": 975.1788087167068,
      "w": 235.7138440677966,
      "h": 203.56990605326877,
      "id": "ui-rect-2",
      "Category": "Medium bus",
      "Occlusion": "Partial occlusion (0%~35%)",
      "Direction": "Front",
      "Truncation": "No truncation (0%)"
    },
    {
      "Object_type": "Vehicles",
      "x": 340.54047457627115,
      "y": 1038.7173268765132,
      "w": 149.06227990314767,
      "h": 73.57137820823245,
      "id": "ui-rect-3",
      "Category": "Sedan",
      "Occlusion": "Others (more than 50%)",
      "Direction": "Left",
      "Truncation": "No truncation (0%)"
    },
    {
      "Object_type": "Vehicles",
      "x": 378.79914769975784,
      "y": 1036.8564842615012,
      "w": 111.7352832929782,
      "h": 89.79585472154963,
      "id": "ui-rect-4",
      "Category": "Sedan",
      "Occlusion": "Occlusion for most parts (35%~50%)",
      "Direction": "Front",
      "Truncation": "No truncation (0%)"
    },
    {
      "Object_type": "Vehicles",
      "x": 397.45778208232446,
      "y": 1025.8891234866828,
      "w": 195.00030217917674,
      "h": 137.14315932203388,
      "id": "ui-rect-5",
      "Category": "Sedan",
      "Occlusion": "No occlusion (0%)",
      "Direction": "Front",
      "Truncation": "No truncation (0%)"
    },
    {
      "Object_type": "Vehicles",
      "x": 544.2603777239709,
      "y": 1041.638818401937,
      "w": 104.95717191283293,
      "h": 78.71740823244552,
      "id": "ui-rect-6",
      "Category": "Sedan",
      "Occlusion": "Partial occlusion (0%~35%)",
      "Direction": "Front",
      "Truncation": "No truncation (0%)"
    },
    {
      "Object_type": "Pedestrians",
      "x": 640.0168910411621,
      "y": 1008.7994963680386,
      "w": 51.020350605326875,
      "h": 185.20467602905566,
      "id": "ui-rect-7",
      "Category": "Standing people",
      "Occlusion": "Partial occlusion (0%~35%)",
      "Direction": "Left",
      "Truncation": "No truncation (0%)"
    },
    {
      "Object_type": "Vehicles",
      "x": 628.2399225181598,
      "y": 1037.3930847457625,
      "w": 46.33529491525424,
      "h": 41.12870121065375,
      "id": "ui-rect-8",
      "Category": "Sedan",
      "Occlusion": "Others (more than 50%)",
      "Direction": "Back",
      "Truncation": "No truncation (0%)"
    },
    {
      "Object_type": "Vehicles",
      "x": 689.2962711864407,
      "y": 1033.2509055690073,
      "w": 47.37617433414043,
      "h": 44.82496852300242,
      "id": "ui-rect-9",
      "Category": "Sedan",
      "Occlusion": "No occlusion (0%)",
      "Direction": "Back",
      "Truncation": "No truncation (0%)"
    },
    {
      "Object_type": "Vehicles",
      "x": 704.6066440677965,
      "y": 1038.7173268765132,
      "w": 44.096321549636805,
      "h": 37.90062566585956,
      "id": "ui-rect-10",
      "Category": "Sedan",
      "Occlusion": "Partial occlusion (0%~35%)",
      "Direction": "Back",
      "Truncation": "No truncation (0%)"
    },
    {
      "Object_type": "Vehicles",
      "x": 707.5155835351089,
      "y": 1021.2291719128328,
      "w": 43.3673607748184,
      "h": 53.93556610169491,
      "id": "ui-rect-12",
      "Category": "Medium bus",
      "Occlusion": "Partial occlusion (0%~35%)",
      "Direction": "Back",
      "Truncation": "No truncation (0%)"
    },
    {
      "Object_type": "Traffic lights",
      "x": 641.4886198547215,
      "y": 949.6479225181597,
      "w": 23.19996900726392,
      "h": 11.399998837772396,
      "id": "ui-rect-13",
      "Category": "Traffic light frame",
      "Color": "no",
      "Association_id": "no",
      "Number": "no"
    },
    {
      "Object_type": "Traffic lights",
      "x": 678.2849782082325,
      "y": 950.4575302663437,
      "w": 22.80024871670702,
      "h": 13.000009685230024,
      "id": "ui-rect-14",
      "Category": "Traffic light frame",
      "Color": "no",
      "Association_id": "no",
      "Number": "no"
    },
    {
      "Object_type": "Traffic lights",
      "x": 712.4893365617432,
      "y": 952.8518353510896,
      "w": 23.000046101694913,
      "h": 13.000009685230024,
      "id": "ui-rect-15",
      "Category": "Traffic light frame",
      "Color": "no",
      "Association_id": "no",
      "Number": "no"
    },
    {
      "Object_type": "Vehicles",
      "x": 732.4439709443099,
      "y": 954.2513898305084,
      "w": 282.99870217917675,
      "h": 276.99850460048424,
      "id": "ui-rect-17",
      "Category": "Sedan",
      "Occlusion": "Partial occlusion (0%~35%)",
      "Direction": "Back",
      "Truncation": "No truncation (0%)"
    },
    {
      "Object_type": "Vehicles",
      "x": 960.4426924939467,
      "y": 1016.2491428571427,
      "w": 140.99946537530263,
      "h": 144.99949249394672,
      "id": "ui-rect-18",
      "Category": "Sedan",
      "Occlusion": "Partial occlusion (0%~35%)",
      "Direction": "Back",
      "Truncation": "No truncation (0%)"
    },
    {
      "Object_type": "Vehicles",
      "x": 991.0414721549636,
      "y": 1005.2190217917675,
      "w": 142.34787021791766,
      "h": 71.93866924939466,
      "id": "ui-rect-19",
      "Category": "City bus",
      "Occlusion": "Partial occlusion (0%~35%)",
      "Direction": "Right",
      "Truncation": "No truncation (0%)"
    },
    {
      "Object_type": "Pedestrians",
      "x": 1168.2859467312346,
      "y": 1049.2485036319613,
      "w": 25.999956610169487,
      "h": 49.59977142857143,
      "id": "ui-rect-20",
      "Category": "Cyclists",
      "Occlusion": "Partial occlusion (0%~35%)",
      "Direction": "Back",
      "Truncation": "No truncation (0%)"
    },
    {
      "Object_type": "Pedestrians",
      "x": 1181.889239709443,
      "y": 1052.4492784503632,
      "w": 31.399914769975783,
      "h": 61.599852784503625,
      "id": "ui-rect-21",
      "Category": "Cyclists",
      "Occlusion": "Partial occlusion (0%~35%)",
      "Direction": "Left",
      "Truncation": "No truncation (0%)"
    },
    {
      "Object_type": "Pedestrians",
      "x": 1200.6577046004843,
      "y": 1051.7087070217917,
      "w": 29.15444571428571,
      "h": 74.96842227602905,
      "id": "ui-rect-22",
      "Category": "Cyclists",
      "Occlusion": "No occlusion (0%)",
      "Direction": "Back",
      "Truncation": "No truncation (0%)"
    },
    {
      "Object_type": "Vehicles",
      "x": 1232.6215205811136,
      "y": 1002.7494043583533,
      "w": 383.60030992736074,
      "h": 267.4015147699758,
      "id": "ui-rect-23",
      "Category": "Sedan",
      "Occlusion": "Occlusion for most parts (35%~50%)",
      "Direction": "Back",
      "Truncation": "No truncation (0%)"
    },
    {
      "Object_type": "Vehicles",
      "x": 1284.6749055690073,
      "y": 845.2493171912832,
      "w": 985.8763002421307,
      "h": 725.1982953995157,
      "id": "ui-rect-24",
      "Category": "Sedan",
      "Occlusion": "No occlusion (0%)",
      "Direction": "Back",
      "Truncation": "No truncation (0%)"
    },
    {
      "Object_type": "Pedestrians",
      "x": 2103.178924939467,
      "y": 1024.464464891041,
      "w": 66.42862953995157,
      "h": 181.42870314769974,
      "id": "ui-rect-25",
      "Category": "Cyclists",
      "Occlusion": "Others (more than 50%)",
      "Direction": "Back",
      "Truncation": "No truncation (0%)"
    },
    {
      "Object_type": "Vehicles",
      "x": 2148.887244552058,
      "y": 1017.3223438256657,
      "w": 243.57206004842612,
      "h": 109.28574915254237,
      "id": "ui-rect-26",
      "Category": "Sedan",
      "Occlusion": "Partial occlusion (0%~35%)",
      "Direction": "Front",
      "Truncation": "No truncation (0%)"
    },
    {
      "Object_type": "Pedestrians",
      "x": 2353.793317191283,
      "y": 1022.0670217917674,
      "w": 51.53059176755447,
      "h": 112.24489685230023,
      "id": "ui-rect-27",
      "Category": "E-bike riders/moto-cyclists",
      "Occlusion": "No occlusion (0%)",
      "Direction": "Right",
      "Truncation": "No truncation (0%)"
    },
    {
      "Object_type": "Pedestrians",
      "x": 2430.8347118644065,
      "y": 1012.8820532687652,
      "w": 45.40801162227603,
      "h": 121.93885133171912,
      "id": "ui-rect-28",
      "Category": "Standing people",
      "Occlusion": "No occlusion (0%)",
      "Direction": "Back",
      "Truncation": "No truncation (0%)"
    }
  ],
  "Workload": {
    "Pedestrians": 7,
    "Vehicles": 17,
    "Traffic lights": 3,
    "Indication signs": 0,
    "Prohibitory signs": 0,
    "MISC": 0,
    "Dontcare": 0
  }
}