{
  "boxs": [
    {
      "Object_type": "Pedestrians",
      "x": 710.7763599999998,
      "y": 1559.4994799999997,
      "w": 26.293791999999996,
      "h": 63.77545999999998,
      "id": "ui-rect-1",
      "Category": "Standing people",
      "Occlusion": "Partial occlusion (0%~35%)",
      "Direction": "Front",
      "Truncation": "No truncation (0%)"
    },
    {
      "Object_type": "MISC",
      "x": 702.4443999999999,
      "y": 1584.4933999999996,
      "w": 23.167395999999993,
      "h": 38.00498799999999,
      "id": "ui-rect-2",
      "Category": "Pedestrians"
    },
    {
      "Object_type": "Pedestrians",
      "x": 891.5001199999997,
      "y": 1560.0208399999997,
      "w": 24.133283999999996,
      "h": 48.937671999999985,
      "id": "ui-rect-3",
      "Category": "E-bike riders/moto-cyclists",
      "Occlusion": "No occlusion (0%)",
      "Direction": "Front",
      "Truncation": "No truncation (0%)"
    },
    {
      "Object_type": "Pedestrians",
      "x": 862.0138799999997,
      "y": 1564.7287599999997,
      "w": 14.056571199999995,
      "h": 37.224515999999994,
      "id": "ui-rect-5",
      "Category": "E-bike riders/moto-cyclists",
      "Occlusion": "No occlusion (0%)",
      "Direction": "Front",
      "Truncation": "No truncation (0%)"
    },
    {
      "Object_type": "Pedestrians",
      "x": 867.4783599999998,
      "y": 1568.0999599999998,
      "w": 17.180419199999996,
      "h": 31.236911999999993,
      "id": "ui-rect-6",
      "Category": "E-bike riders/moto-cyclists",
      "Occlusion": "Occlusion for most parts (35%~50%)",
      "Direction": "Front",
      "Truncation": "No truncation (0%)"
    },
    {
      "Object_type": "Pedestrians",
      "x": 837.0277999999998,
      "y": 1568.6213199999997,
      "w": 19.523422799999995,
      "h": 31.75768399999999,
      "id": "ui-rect-7",
      "Category": "E-bike riders/moto-cyclists",
      "Occlusion": "No occlusion (0%)",
      "Direction": "Front",
      "Truncation": "No truncation (0%)"
    },
    {
      "Object_type": "Pedestrians",
      "x": 819.5779199999997,
      "y": 1571.4789999999996,
      "w": 16.399496399999993,
      "h": 28.63383599999999,
      "id": "ui-rect-8",
      "Category": "E-bike riders/moto-cyclists",
      "Occlusion": "No occlusion (0%)",
      "Direction": "Front",
      "Truncation": "No truncation (0%)"
    },
    {
      "Object_type": "Pedestrians",
      "x": 793.3001999999998,
      "y": 1566.0007999999996,
      "w": 10.600150399999999,
      "h": 33.60047599999999,
      "id": "ui-rect-9",
      "Category": "Standing people",
      "Occlusion": "Others (more than 50%)",
      "Direction": "Front",
      "Truncation": "No truncation (0%)"
    },
    {
      "Object_type": "Pedestrians",
      "x": 800.9069599999998,
      "y": 1568.1999199999996,
      "w": 10.799991999999998,
      "h": 29.800427999999993,
      "id": "ui-rect-10",
      "Category": "Standing people",
      "Occlusion": "Others (more than 50%)",
      "Direction": "Right",
      "Truncation": "No truncation (0%)"
    },
    {
      "Object_type": "Vehicles",
      "x": 975.7644399999998,
      "y": 1553.3999599999997,
      "w": 66.00005999999998,
      "h": 48.860447999999984,
      "id": "ui-rect-11",
      "Category": "Sedan",
      "Occlusion": "No occlusion (0%)",
      "Direction": "Front",
      "Truncation": "No truncation (0%)"
    },
    {
      "Object_type": "Vehicles",
      "x": 992.9007199999998,
      "y": 1538.4000799999997,
      "w": 55.599907999999985,
      "h": 54.999951999999986,
      "id": "ui-rect-12",
      "Category": "Sedan",
      "Occlusion": "Occlusion for most parts (35%~50%)",
      "Direction": "Front",
      "Truncation": "No truncation (0%)"
    },
    {
      "Object_type": "Prohibitory signs",
      "x": 920.3003599999997,
      "y": 1396.7998799999998,
      "w": 29.599919999999994,
      "h": 25.59995199999999,
      "id": "ui-rect-13",
      "Category": "Driving prohibited",
      "Content": "no"
    },
    {
      "Object_type": "Traffic lights",
      "x": 1103.8857199999998,
      "y": 1357.5998799999998,
      "w": 17.799994799999997,
      "h": 43.200163999999994,
      "id": "ui-rect-14",
      "Category": "Traffic light frame",
      "Color": "no",
      "Association_id": "no",
      "Number": "no"
    },
    {
      "Object_type": "Traffic lights",
      "x": 1123.4994399999998,
      "y": 1355.6006799999998,
      "w": 17.999855999999998,
      "h": 41.59982399999999,
      "id": "ui-rect-15",
      "Category": "Traffic light frame",
      "Color": "no",
      "Association_id": "no",
      "Number": "no"
    },
    {
      "Object_type": "Traffic lights",
      "x": 1221.4994399999998,
      "y": 1456.4073999999998,
      "w": 9.400003199999997,
      "h": 20.799715999999993,
      "id": "ui-rect-16",
      "Category": "Traffic light frame",
      "Color": "no",
      "Association_id": "no",
      "Number": "no"
    },
    {
      "Object_type": "Prohibitory signs",
      "x": 1280.4993599999998,
      "y": 1391.7999199999997,
      "w": 27.20009599999999,
      "h": 28.200283999999993,
      "id": "ui-rect-19",
      "Category": "Speed limit",
      "Content": "50"
    },
    {
      "Object_type": "Traffic lights",
      "x": 1337.3001599999998,
      "y": 1452.2071199999998,
      "w": 8.399991599999998,
      "h": 19.800115999999996,
      "id": "ui-rect-20",
      "Category": "Traffic light frame",
      "Color": "no",
      "Association_id": "no",
      "Number": "no"
    },
    {
      "Object_type": "Traffic lights",
      "x": 1724.7000399999995,
      "y": 1341.0006399999995,
      "w": 23.000011999999995,
      "h": 46.60017599999999,
      "id": "ui-rect-21",
      "Category": "Traffic light frame",
      "Color": "no",
      "Association_id": "no",
      "Number": "no"
    },
    {
      "Object_type": "Traffic lights",
      "x": 1746.7990399999996,
      "y": 1341.8003199999996,
      "w": 18.726565199999996,
      "h": 42.95085199999999,
      "id": "ui-rect-22",
      "Category": "Traffic light frame",
      "Color": "no",
      "Association_id": "no",
      "Number": "no"
    },
    {
      "Object_type": "Traffic lights",
      "x": 1749.2999999999995,
      "y": 1367.0000399999997,
      "w": 12.399998799999997,
      "h": 15.399994399999997,
      "id": "ui-rect-23",
      "Category": "Ordinary light",
      "Color": "Green",
      "Association_id": "ui-rect-22",
      "Number": "no"
    },
    {
      "Object_type": "Pedestrians",
      "x": 1492.7007199999996,
      "y": 1535.1993999999995,
      "w": 10.199996799999997,
      "h": 25.199915999999995,
      "id": "ui-rect-24",
      "Category": "Standing people",
      "Occlusion": "Partial occlusion (0%~35%)",
      "Direction": "Back",
      "Truncation": "No truncation (0%)"
    },
    {
      "Object_type": "Traffic lights",
      "x": 2405.645199999999,
      "y": 1430.1002799999997,
      "w": 13.306851599999996,
      "h": 35.66219999999999,
      "id": "ui-rect-25",
      "Category": "Traffic light frame",
      "Color": "no",
      "Association_id": "no",
      "Number": "no"
    },
    {
      "Object_type": "Traffic lights",
      "x": 2406.4291999999996,
      "y": 1442.8931999999995,
      "w": 8.590150799999996,
      "h": 15.358207199999997,
      "id": "ui-rect-26",
      "Category": "Ordinary light",
      "Color": "Green",
      "Association_id": "ui-rect-25",
      "Number": "no"
    },
    {
      "Object_type": "MISC",
      "x": 339.8326399999999,
      "y": 1446.7935999999995,
      "w": 28.061123999999992,
      "h": 36.07869999999999,
      "id": "ui-rect-27",
      "Category": "Indication signs"
    }
  ],
  "Workload": {
    "Pedestrians": 9,
    "Vehicles": 2,
    "Traffic lights": 9,
    "Indication signs": 0,
    "Prohibitory signs": 2,
    "MISC": 2,
    "Dontcare": 0
  }
}