{
  "boxs": [
    {
      "Object_type": "Pedestrians",
      "x": 590.9419599999998,
      "y": 860.4439199999998,
      "w": 727.1560799999999,
      "h": 1070.1580399999998,
      "id": "ui-rect-0",
      "Category": "E-bike riders/moto-cyclists",
      "Occlusion": "Partial occlusion (0%~35%)",
      "Direction": "Back",
      "Truncation": "No truncation (0%)"
    },
    {
      "Object_type": "Vehicles",
      "x": 1.0714281199999998,
      "y": 1071.4281199999998,
      "w": 117.14273199999997,
      "h": 102.14304799999996,
      "id": "ui-rect-1",
      "Category": "Sedan",
      "Occlusion": "No occlusion (0%)",
      "Direction": "Right",
      "Truncation": "Others (more than 50%)"
    },
    {
      "Object_type": "Vehicles",
      "x": 1.7857050399999996,
      "y": 1005.7210799999998,
      "w": 240.00003999999993,
      "h": 139.28583199999997,
      "id": "ui-rect-2",
      "Category": "Sedan",
      "Occlusion": "Partial occlusion (0%~35%)",
      "Direction": "Left",
      "Truncation": "Truncation for most parts (35%~50%)"
    },
    {
      "Object_type": "Pedestrians",
      "x": 226.78571999999994,
      "y": 1037.1418399999998,
      "w": 84.28587999999998,
      "h": 94.28579999999997,
      "id": "ui-rect-3",
      "Category": "E-bike riders/moto-cyclists",
      "Occlusion": "Partial occlusion (0%~35%)",
      "Direction": "Left",
      "Truncation": "No truncation (0%)"
    },
    {
      "Object_type": "Vehicles",
      "x": 201.78591999999995,
      "y": 1052.1417199999999,
      "w": 151.42763999999997,
      "h": 70.71425199999997,
      "id": "ui-rect-4",
      "Category": "Sedan",
      "Occlusion": "Others (more than 50%)",
      "Direction": "Left",
      "Truncation": "No truncation (0%)"
    },
    {
      "Object_type": "Vehicles",
      "x": 319.64071999999993,
      "y": 1041.4283599999997,
      "w": 380.7162799999999,
      "h": 152.14225599999995,
      "id": "ui-rect-5",
      "Category": "Sedan",
      "Occlusion": "Occlusion for most parts (35%~50%)",
      "Direction": "Right",
      "Truncation": "No truncation (0%)"
    },
    {
      "Object_type": "Vehicles",
      "x": 504.6431599999999,
      "y": 1049.2918799999998,
      "w": 440.7157999999999,
      "h": 154.28590799999995,
      "id": "ui-rect-6",
      "Category": "Sedan",
      "Occlusion": "Others (more than 50%)",
      "Direction": "Right",
      "Truncation": "No truncation (0%)"
    },
    {
      "Object_type": "Vehicles",
      "x": 588.2136399999998,
      "y": 1047.8591199999996,
      "w": 662.1428799999998,
      "h": 214.28483999999995,
      "id": "ui-rect-7",
      "Category": "Sedan",
      "Occlusion": "Others (more than 50%)",
      "Direction": "Right",
      "Truncation": "No truncation (0%)"
    },
    {
      "Object_type": "Vehicles",
      "x": 873.2152799999998,
      "y": 1035.7071199999998,
      "w": 270.7151999999999,
      "h": 125.71420399999997,
      "id": "ui-rect-8",
      "Category": "Sedan",
      "Occlusion": "Others (more than 50%)",
      "Direction": "Left",
      "Truncation": "No truncation (0%)"
    },
    {
      "Object_type": "Vehicles",
      "x": 1292.5004399999996,
      "y": 1099.2934399999997,
      "w": 152.85765599999996,
      "h": 57.142623999999984,
      "id": "ui-rect-9",
      "Category": "Sedan",
      "Occlusion": "Others (more than 50%)",
      "Direction": "Left",
      "Truncation": "No truncation (0%)"
    },
    {
      "Object_type": "Pedestrians",
      "x": 1495.3486799999996,
      "y": 1057.8551199999997,
      "w": 279.9997199999999,
      "h": 225.71359999999993,
      "id": "ui-rect-10",
      "Category": "E-bike riders/moto-cyclists",
      "Occlusion": "No occlusion (0%)",
      "Direction": "Right",
      "Truncation": "No truncation (0%)"
    },
    {
      "Object_type": "Pedestrians",
      "x": 2010.3523999999995,
      "y": 1049.9994399999998,
      "w": 202.85999999999996,
      "h": 229.28471999999994,
      "id": "ui-rect-11",
      "Category": "Cyclists",
      "Occlusion": "No occlusion (0%)",
      "Direction": "Right",
      "Truncation": "No truncation (0%)"
    },
    {
      "Object_type": "Pedestrians",
      "x": 2397.4915999999994,
      "y": 1087.8587999999997,
      "w": 192.14291599999996,
      "h": 230.71355999999994,
      "id": "ui-rect-12",
      "Category": "E-bike riders/moto-cyclists",
      "Occlusion": "No occlusion (0%)",
      "Direction": "Left",
      "Truncation": "Minor truncation (0%~15%)"
    },
    {
      "Object_type": "Vehicles",
      "x": 1351.4199999999996,
      "y": 856.5219599999997,
      "w": 1232.8399999999997,
      "h": 397.8780399999999,
      "id": "ui-rect-13",
      "Category": "City bus",
      "Occlusion": "Partial occlusion (0%~35%)",
      "Direction": "Right",
      "Truncation": "Minor truncation (0%~15%)"
    },
    {
      "Object_type": "Traffic lights",
      "x": 503.21431999999993,
      "y": 960.0001599999997,
      "w": 32.14301999999999,
      "h": 70.71425199999997,
      "id": "ui-rect-14",
      "Category": "Traffic light frame",
      "Color": "no",
      "Association_id": "no",
      "Number": "no"
    },
    {
      "Object_type": "Traffic lights",
      "x": 285.35639999999995,
      "y": 817.8570399999998,
      "w": 32.14301999999999,
      "h": 64.28564799999998,
      "id": "ui-rect-16",
      "Category": "Traffic light frame",
      "Color": "no",
      "Association_id": "no",
      "Number": "no"
    },
    {
      "Object_type": "Traffic lights",
      "x": 157.50011199999997,
      "y": 815.7147599999997,
      "w": 38.57162399999999,
      "h": 63.57142399999998,
      "id": "ui-rect-17",
      "Category": "Traffic light frame",
      "Color": "no",
      "Association_id": "no",
      "Number": "no"
    },
    {
      "Object_type": "Traffic lights",
      "x": 159.64278399999998,
      "y": 820.0012799999998,
      "w": 20.000035999999994,
      "h": 16.428563199999996,
      "id": "ui-rect-18",
      "Category": "Ordinary light",
      "Color": "Red",
      "Association_id": "ui-rect-17",
      "Number": "no"
    },
    {
      "Object_type": "Traffic lights",
      "x": 166.78580799999997,
      "y": 839.9991599999998,
      "w": 16.428563199999996,
      "h": 14.285714799999997,
      "id": "ui-rect-19",
      "Category": "Numbers",
      "Color": "Red",
      "Association_id": "ui-rect-17",
      "Number": "73"
    },
    {
      "Object_type": "Traffic lights",
      "x": 23.928659999999997,
      "y": 812.1436399999998,
      "w": 33.57146799999999,
      "h": 61.428555999999986,
      "id": "ui-rect-20",
      "Category": "Traffic light frame",
      "Color": "no",
      "Association_id": "no",
      "Number": "no"
    },
    {
      "Object_type": "Traffic lights",
      "x": 31.07148799999999,
      "y": 834.2857599999999,
      "w": 17.857148399999996,
      "h": 14.999997599999997,
      "id": "ui-rect-21",
      "Category": "Numbers",
      "Color": "Red",
      "Association_id": "ui-rect-20",
      "Number": "73"
    },
    {
      "Object_type": "Traffic lights",
      "x": 26.785751999999995,
      "y": 813.5705199999998,
      "w": 20.000035999999994,
      "h": 18.571431199999996,
      "id": "ui-rect-22",
      "Category": "Ordinary light",
      "Color": "Red",
      "Association_id": "ui-rect-20",
      "Number": "no"
    }
  ],
  "Workload": {
    "Pedestrians": 5,
    "Vehicles": 9,
    "Traffic lights": 8,
    "Indication signs": 0,
    "Prohibitory signs": 0,
    "MISC": 0,
    "Dontcare": 0
  }
}